apeek/__init__.py
apeek/__main__.py
apeek/waveform.py
apeek-0.2.0.dist-info/entry_points.txt
apeek-0.2.0.dist-info/WHEEL
apeek-0.2.0.dist-info/METADATA
apeek-0.2.0.dist-info/RECORD
